propgrid/__init__.py
propgrid/enumtype.py
propgrid/formatters.py
propgrid/prop.py
propgrid/propart.py
propgrid/propgrid.py
propgrid/propxpm.py
propgrid/validators.py
propgrid/version.py
propgrid-0.1.6.dist-info/LICENSE
propgrid-0.1.6.dist-info/METADATA
propgrid-0.1.6.dist-info/WHEEL
propgrid-0.1.6.dist-info/top_level.txt
propgrid-0.1.6.dist-info/RECORD
