Metadata-Version: 2.1
Name: propgrid
Version: 0.1.6
Summary: A lightweight propgrid in wxpython to show/config data
Author-email: Tianzhu Qiao <tq@feiyilin.com>
License: MIT License
Project-URL: Homepage, https://github.com/tianzhuqiao/propgrid
Classifier: Operating System :: OS Independent
Requires-Python: >=3.0
License-File: LICENSE
Requires-Dist: wxpython>=4.2.1
